larry_utils/__init__.py
larry_utils/create.py
larry_utils-2.0.3.dist-info/METADATA
larry_utils-2.0.3.dist-info/WHEEL
larry_utils-2.0.3.dist-info/top_level.txt
larry_utils-2.0.3.dist-info/RECORD
