Metadata-Version: 2.1
Name: larry-utils
Version: 2.0.3
Summary: larry produced utils for projects
Home-page: UNKNOWN
License: UNKNOWN
Platform: UNKNOWN
